YaodongXiuxiudeshi/README.md
YaodongXiuxiudeshi/__init__.py
YaodongXiuxiudeshi/__main__.py
YaodongXiuxiudeshi/file.epub
YaodongXiuxiudeshi/index.html
YaodongXiuxiudeshi/css/__init__.py
YaodongXiuxiudeshi/css/annotations.css
YaodongXiuxiudeshi/css/main.css
YaodongXiuxiudeshi/css/normalize.css
YaodongXiuxiudeshi/css/popup.css
YaodongXiuxiudeshi/font/__init__.py
YaodongXiuxiudeshi/font/fontello.eot
YaodongXiuxiudeshi/font/fontello.svg
YaodongXiuxiudeshi/font/fontello.ttf
YaodongXiuxiudeshi/font/fontello.woff
YaodongXiuxiudeshi/img/__init__.py
YaodongXiuxiudeshi/img/annotator-glyph-sprite.png
YaodongXiuxiudeshi/img/annotator-icon-sprite.png
YaodongXiuxiudeshi/img/apple-touch-icon.png
YaodongXiuxiudeshi/img/cancelfullscreen.png
YaodongXiuxiudeshi/img/close.png
YaodongXiuxiudeshi/img/fullscreen.png
YaodongXiuxiudeshi/img/loader.gif
YaodongXiuxiudeshi/img/menu-icon.png
YaodongXiuxiudeshi/img/save.png
YaodongXiuxiudeshi/img/saved.png
YaodongXiuxiudeshi/img/settings-s.png
YaodongXiuxiudeshi/img/settings.png
YaodongXiuxiudeshi/img/star.png
YaodongXiuxiudeshi/js/__init__.py
YaodongXiuxiudeshi/js/epub.js
YaodongXiuxiudeshi/js/epub.min.js
YaodongXiuxiudeshi/js/epub.min.map
YaodongXiuxiudeshi/js/hooks.min.js
YaodongXiuxiudeshi/js/hooks.min.map
YaodongXiuxiudeshi/js/reader.js
YaodongXiuxiudeshi/js/reader.js.map
YaodongXiuxiudeshi/js/reader.min.js
YaodongXiuxiudeshi/js/reader.min.map
YaodongXiuxiudeshi/js/hooks/__init__.py
YaodongXiuxiudeshi/js/hooks/extensions/__init__.py
YaodongXiuxiudeshi/js/hooks/extensions/highlight.js
YaodongXiuxiudeshi/js/libs/__init__.py
YaodongXiuxiudeshi/js/libs/jquery.min.js
YaodongXiuxiudeshi/js/libs/localforage.min.js
YaodongXiuxiudeshi/js/libs/screenfull.js
YaodongXiuxiudeshi/js/libs/screenfull.min.js
YaodongXiuxiudeshi/js/libs/zip.min.js
YaodongXiuxiudeshi/js/plugins/__init__.py
YaodongXiuxiudeshi/js/plugins/hypothesis.js
YaodongXiuxiudeshi/js/plugins/search.js
yaodong_xiuxiudeshi-2022.10.11.0.dist-info/METADATA
yaodong_xiuxiudeshi-2022.10.11.0.dist-info/WHEEL
yaodong_xiuxiudeshi-2022.10.11.0.dist-info/entry_points.txt
yaodong_xiuxiudeshi-2022.10.11.0.dist-info/top_level.txt
yaodong_xiuxiudeshi-2022.10.11.0.dist-info/RECORD
